staticflow/__init__.py
staticflow/admin/__init__.py
staticflow/admin/package-lock.json
staticflow/admin/package.json
staticflow/admin/static/css/admin.css
staticflow/admin/static/css/block-editor.css
staticflow/admin/static/css/preview.css
staticflow/admin/static/css/tiptap-editor.css
staticflow/admin/static/dist/admin.js
staticflow/admin/static/dist/admin.js.LICENSE.txt
staticflow/admin/static/dist/deploy.js
staticflow/admin/static/dist/deploy.js.LICENSE.txt
staticflow/admin/static/dist/markdown-preprocessor.js
staticflow/admin/static/dist/tiptap-audio.js
staticflow/admin/static/dist/tiptap-audio.js.LICENSE.txt
staticflow/admin/static/dist/tiptap-bubblemenu.js
staticflow/admin/static/dist/tiptap-code-block.js
staticflow/admin/static/dist/tiptap-dnd-blocks.js
staticflow/admin/static/dist/tiptap-dnd-blocks.js.LICENSE.txt
staticflow/admin/static/dist/tiptap-dnd-nodeview.js
staticflow/admin/static/dist/tiptap-drop-indicator.js
staticflow/admin/static/dist/tiptap-editor.js
staticflow/admin/static/dist/tiptap-editor.js.LICENSE.txt
staticflow/admin/static/dist/tiptap-image.js
staticflow/admin/static/dist/tiptap-image.js.LICENSE.txt
staticflow/admin/static/dist/tiptap-math.js
staticflow/admin/static/dist/tiptap-mermaid.js
staticflow/admin/static/dist/tiptap-paragraph-dnd.js
staticflow/admin/static/dist/tiptap-toolbar.js
staticflow/admin/static/dist/tiptap-video.js
staticflow/admin/static/dist/tiptap-video.js.LICENSE.txt
staticflow/admin/static/js/admin.js
staticflow/admin/static/js/deploy.js
staticflow/admin/static/js/markdown-preprocessor.js
staticflow/admin/static/js/tiptap-audio.js
staticflow/admin/static/js/tiptap-bubblemenu.js
staticflow/admin/static/js/tiptap-code-block.js
staticflow/admin/static/js/tiptap-dnd-blocks.js
staticflow/admin/static/js/tiptap-dnd-nodeview.js
staticflow/admin/static/js/tiptap-drop-indicator.js
staticflow/admin/static/js/tiptap-editor.js
staticflow/admin/static/js/tiptap-image.js
staticflow/admin/static/js/tiptap-math.js
staticflow_framework-0.1.7.dist-info/LICENSE
staticflow_framework-0.1.7.dist-info/METADATA
staticflow_framework-0.1.7.dist-info/WHEEL
staticflow_framework-0.1.7.dist-info/RECORD
